{
  "snapshot_time": "2026/05/09 08:15:14",
  "today_sales": "0人(0人)",
  "today_customers": "0人(0人)",
  "today_avg": "0人/0人",
  "today_active_staff": "0人/0人",
  "today_reservation_rate": "0件/16件",
  "current_store_code": "001",
  "weekly_reservations": [
    {
      "date": "5/9(土)",
      "count": "16件"
    },
    {
      "date": "5/10(日)",
      "count": "8件"
    },
    {
      "date": "5/11(月)",
      "count": "7件"
    },
    {
      "date": "5/12(火)",
      "count": "7件"
    },
    {
      "date": "5/13(水)",
      "count": "7件"
    },
    {
      "date": "5/14(木)",
      "count": "3件"
    },
    {
      "date": "5/15(金)",
      "count": "4件"
    }
  ]
}